[{"window":"main","id":"chrome","kind":"Chrome","rect":{"x":0.0,"y":0.0,"w":1100.0,"h":32.0},"layer":"","label":null},{"window":"main","id":"chrome:drag","kind":"DragHandle","rect":{"x":0.0,"y":0.0,"w":890.0,"h":32.0},"layer":"","label":null},{"window":"main","id":"chrome:new_win","kind":"Button","rect":{"x":890.0,"y":0.0,"w":36.0,"h":32.0},"layer":"","label":null},{"window":"main","id":"chrome:close_win","kind":"Button","rect":{"x":926.0,"y":0.0,"w":36.0,"h":32.0},"layer":"","label":null},{"window":"main","id":"chrome:min","kind":"Button","rect":{"x":962.0,"y":0.0,"w":46.0,"h":32.0},"layer":"","label":null},{"window":"main","id":"chrome:max","kind":"Button","rect":{"x":1008.0,"y":0.0,"w":46.0,"h":32.0},"layer":"","label":null},{"window":"main","id":"chrome:close","kind":"Button","rect":{"x":1054.0,"y":0.0,"w":46.0,"h":32.0},"layer":"","label":null}]